tamingnifty/__init__.py
tamingnifty/connect_definedge.py
tamingnifty/ta.py
tamingnifty/tick_streamer.py
tamingnifty/utils.py
tamingnifty-1.0.9.dist-info/licenses/LICENSE
tamingnifty-1.0.9.dist-info/licenses/LICENSE.md
tamingnifty-1.0.9.dist-info/METADATA
tamingnifty-1.0.9.dist-info/WHEEL
tamingnifty-1.0.9.dist-info/top_level.txt
tamingnifty-1.0.9.dist-info/RECORD
