Metadata-Version: 2.4
Name: tamingnifty
Version: 1.0.9
Summary: A library for converting OHLC to Noiseless Charts (Renko and PNF)
Author: Sugam Gupta
Author-email: Sugam Gupta <sugam192@gmail.com>
License: MIT License
Classifier: Programming Language :: Python :: 3
Classifier: License :: OSI Approved :: MIT License
Classifier: Operating System :: OS Independent
Requires-Python: >=3.7
License-File: LICENSE
License-File: LICENSE.md
Requires-Dist: pymongo
Requires-Dist: requests
Requires-Dist: pandas
Requires-Dist: slack_sdk
Requires-Dist: python-dotenv
Dynamic: author
Dynamic: license-file
Dynamic: requires-python
